[
  {
    "content_id": 296168,
    "reference_id": 186726,
    "title": "Baskets of Pastries",
    "media_type": "Image",
    "index_reference": "baskets of pastries",
    "language": "eng",
    "content": "<h3>Image Content</h3>\n<block>\n<p><img src='https://cdn.aquifer.bible/aquifer-content/resources/FIAImages/basket-pastries-holding.jpg' alt='Image' /></p>\n<p><a href='https://cdn.aquifer.bible/aquifer-content/resources/FIAImages/basket-pastries-holding.jpg'>link</a></p>\n</block>",
    "associations": {
      "passage": [
        {
          "start_ref": "01040001",
          "start_ref_usfm": "GEN 40:1",
          "end_ref": "01040023",
          "end_ref_usfm": "GEN 40:23"
        }
      ],
      "resource": []
    }
  }
]