[
  {
    "content_id": 296140,
    "reference_id": 186698,
    "version": "1.0.0",
    "title": "Fine Linen Cloth",
    "media_type": "Image",
    "index_reference": "fine linen cloth",
    "language": "eng",
    "content": "<h3>Image Content</h3>\n<block>\n<p><img src='https://cdn.aquifer.bible/aquifer-content/resources/FIAImages/linen-fine.jpg' alt='Image' /></p>\n<p><a href='https://cdn.aquifer.bible/aquifer-content/resources/FIAImages/linen-fine.jpg'>link</a></p>\n</block>",
    "associations": {
      "passage": [
        {
          "start_ref": "01041037",
          "start_ref_usfm": "GEN 41:37",
          "end_ref": "01041057",
          "end_ref_usfm": "GEN 41:57"
        },
        {
          "start_ref": "02025001",
          "start_ref_usfm": "EXO 25:1",
          "end_ref": "02025009",
          "end_ref_usfm": "EXO 25:9"
        },
        {
          "start_ref": "02028001",
          "start_ref_usfm": "EXO 28:1",
          "end_ref": "02028014",
          "end_ref_usfm": "EXO 28:14"
        },
        {
          "start_ref": "02035001",
          "start_ref_usfm": "EXO 35:1",
          "end_ref": "02035019",
          "end_ref_usfm": "EXO 35:19"
        },
        {
          "start_ref": "02026001",
          "start_ref_usfm": "EXO 26:1",
          "end_ref": "02026014",
          "end_ref_usfm": "EXO 26:14"
        },
        {
          "start_ref": "02039001",
          "start_ref_usfm": "EXO 39:1",
          "end_ref": "02039007",
          "end_ref_usfm": "EXO 39:7"
        }
      ],
      "resource": []
    }
  }
]