[
{
"content_id": "a249",
"reference_id": 0,
"version": "1.0.4",
"title": "播种者",
"media_type": "Image",
"index_reference": "播种者",
"language": "zhs",
"review_level": "None",
"content": "<h3>Image Content</h3>\n<block><p><img src='https://s3.amazonaws.com/cbbt-er.public/media/photos/a249/1000.jpg' alt='Image' width='480' /></p><p><a href='https://s3.amazonaws.com/cbbt-er.public/media/photos/a249/1000.jpg'>link</a></p></block>",
"associations": {
"passage": [
{
"start_ref": "40013001",
"start_ref_usfm": "MAT 13:1",
"end_ref": "40013009",
"end_ref_usfm": "MAT 13:9"
},
{
"start_ref": "40013018",
"start_ref_usfm": "MAT 13:18",
"end_ref": "40013023",
"end_ref_usfm": "MAT 13:23"
},
{
"start_ref": "41004001",
"start_ref_usfm": "MRK 4:1",
"end_ref": "41004020",
"end_ref_usfm": "MRK 4:20"
},
{
"start_ref": "42008004",
"start_ref_usfm": "LUK 8:4",
"end_ref": "42008015",
"end_ref_usfm": "LUK 8:15"
}
],
"resource": [],
"acai": [
{
"id": "keyterm:Parable",
"type": "keyterm",
"confidence": 0.4585,
"match_method": "canonical",
"preferred_label": "Parable"
},
{
"id": "flora:Brier",
"type": "flora",
"confidence": 0.3517,
"match_method": "canonical",
"preferred_label": "Brier"
},
{
"id": "flora:Thistle",
"type": "flora",
"confidence": 0.3474,
"match_method": "canonical",
"preferred_label": "Thistle"
},
{
"id": "flora:Acacia",
"type": "flora",
"confidence": 0.3474,
"match_method": "canonical",
"preferred_label": "Acacia"
},
{
"id": "flora:Boxthorn",
"type": "flora",
"confidence": 0.3474,
"match_method": "canonical",
"preferred_label": "Boxthorn"
},
{
"id": "deity:Lord",
"type": "deity",
"confidence": 0.2787,
"match_method": "canonical",
"preferred_label": "LORD"
},
{
"id": "keyterm:Kingdom",
"type": "keyterm",
"confidence": 0.2787,
"match_method": "canonical",
"preferred_label": "Kingdom"
},
{
"id": "keyterm:Heart",
"type": "keyterm",
"confidence": 0.2787,
"match_method": "canonical",
"preferred_label": "Heart"
},
{
"id": "keyterm:CauseOfJoy",
"type": "keyterm",
"confidence": 0.2787,
"match_method": "canonical",
"preferred_label": "Cause of Joy"
},
{
"id": "keyterm:Believe",
"type": "keyterm",
"confidence": 0.2191,
"match_method": "canonical",
"preferred_label": "Believe"
},
{
"id": "keyterm:Ability",
"type": "keyterm",
"confidence": 0.2191,
"match_method": "canonical",
"preferred_label": "Ability"
},
{
"id": "keyterm:Always",
"type": "keyterm",
"confidence": 0.2191,
"match_method": "canonical",
"preferred_label": "Always"
},
{
"id": "keyterm:DailyLife",
"type": "keyterm",
"confidence": 0.1638,
"match_method": "canonical",
"preferred_label": "Daily Life"
},
{
"id": "keyterm:Honest",
"type": "keyterm",
"confidence": 0.1638,
"match_method": "canonical",
"preferred_label": "Honest"
},
{
"id": "person:Jesus.2",
"type": "person",
"confidence": 0.1596,
"match_method": "canonical",
"preferred_label": "Jesus"
},
{
"id": "keyterm:AskFor",
"type": "keyterm",
"confidence": 0.1596,
"match_method": "canonical",
"preferred_label": "Ask for"
},
{
"id": "keyterm:Salvation",
"type": "keyterm",
"confidence": 0.1596,
"match_method": "canonical",
"preferred_label": "Salvation"
},
{
"id": "deity:Satan",
"type": "deity",
"confidence": 0.1596,
"match_method": "canonical",
"preferred_label": "Satan"
},
{
"id": "keyterm:Forgive",
"type": "keyterm",
"confidence": 0.1596,
"match_method": "canonical",
"preferred_label": "Forgive"
},
{
"id": "keyterm:PutToTheTest",
"type": "keyterm",
"confidence": 0.1596,
"match_method": "canonical",
"preferred_label": "Put to the Test"
},
{
"id": "keyterm:Heaven",
"type": "keyterm",
"confidence": 0.1596,
"match_method": "canonical",
"preferred_label": "Sky"
},
{
"id": "keyterm:Disciple",
"type": "keyterm",
"confidence": 0.1596,
"match_method": "canonical",
"preferred_label": "Be a Disciple"
},
{
"id": "flora:Grain",
"type": "flora",
"confidence": 0.1591,
"match_method": "canonical",
"preferred_label": "Grain"
},
{
"id": "fauna:Bird",
"type": "fauna",
"confidence": 0.1591,
"match_method": "canonical",
"preferred_label": "Bird"
},
{
"id": "flora:Barley",
"type": "flora",
"confidence": 0.1591,
"match_method": "canonical",
"preferred_label": "Barley"
},
{
"id": "fauna:Rooster",
"type": "fauna",
"confidence": 0.1591,
"match_method": "canonical",
"preferred_label": "Rooster"
},
{
"id": "realia:Ship",
"type": "realia",
"confidence": 0.1591,
"match_method": "canonical",
"preferred_label": "Ship"
},
{
"id": "realia:House",
"type": "realia",
"confidence": 0.0996,
"match_method": "canonical",
"preferred_label": "House"
}
]
}
},
{
"content_id": "a250",
"reference_id": 0,
"version": "1.0.4",
"title": "播种者",
"media_type": "Image",
"index_reference": "播种者",
"language": "zhs",
"review_level": "None",
"content": "<h3>Image Content</h3>\n<block><p><img src='https://s3.amazonaws.com/cbbt-er.public/media/photos/a250/1000.jpg' alt='Image' width='480' /></p><p><a href='https://s3.amazonaws.com/cbbt-er.public/media/photos/a250/1000.jpg'>link</a></p></block>",
"associations": {
"passage": [
{
"start_ref": "40013001",
"start_ref_usfm": "MAT 13:1",
"end_ref": "40013009",
"end_ref_usfm": "MAT 13:9"
},
{
"start_ref": "40013018",
"start_ref_usfm": "MAT 13:18",
"end_ref": "40013023",
"end_ref_usfm": "MAT 13:23"
},
{
"start_ref": "41004001",
"start_ref_usfm": "MRK 4:1",
"end_ref": "41004020",
"end_ref_usfm": "MRK 4:20"
},
{
"start_ref": "42008004",
"start_ref_usfm": "LUK 8:4",
"end_ref": "42008015",
"end_ref_usfm": "LUK 8:15"
}
],
"resource": [],
"acai": [
{
"id": "keyterm:Parable",
"type": "keyterm",
"confidence": 0.4585,
"match_method": "canonical",
"preferred_label": "Parable"
},
{
"id": "flora:Brier",
"type": "flora",
"confidence": 0.3517,
"match_method": "canonical",
"preferred_label": "Brier"
},
{
"id": "flora:Thistle",
"type": "flora",
"confidence": 0.3474,
"match_method": "canonical",
"preferred_label": "Thistle"
},
{
"id": "flora:Acacia",
"type": "flora",
"confidence": 0.3474,
"match_method": "canonical",
"preferred_label": "Acacia"
},
{
"id": "flora:Boxthorn",
"type": "flora",
"confidence": 0.3474,
"match_method": "canonical",
"preferred_label": "Boxthorn"
},
{
"id": "deity:Lord",
"type": "deity",
"confidence": 0.2787,
"match_method": "canonical",
"preferred_label": "LORD"
},
{
"id": "keyterm:Kingdom",
"type": "keyterm",
"confidence": 0.2787,
"match_method": "canonical",
"preferred_label": "Kingdom"
},
{
"id": "keyterm:Heart",
"type": "keyterm",
"confidence": 0.2787,
"match_method": "canonical",
"preferred_label": "Heart"
},
{
"id": "keyterm:CauseOfJoy",
"type": "keyterm",
"confidence": 0.2787,
"match_method": "canonical",
"preferred_label": "Cause of Joy"
},
{
"id": "keyterm:Believe",
"type": "keyterm",
"confidence": 0.2191,
"match_method": "canonical",
"preferred_label": "Believe"
},
{
"id": "keyterm:Ability",
"type": "keyterm",
"confidence": 0.2191,
"match_method": "canonical",
"preferred_label": "Ability"
},
{
"id": "keyterm:Always",
"type": "keyterm",
"confidence": 0.2191,
"match_method": "canonical",
"preferred_label": "Always"
},
{
"id": "keyterm:DailyLife",
"type": "keyterm",
"confidence": 0.1638,
"match_method": "canonical",
"preferred_label": "Daily Life"
},
{
"id": "keyterm:Honest",
"type": "keyterm",
"confidence": 0.1638,
"match_method": "canonical",
"preferred_label": "Honest"
},
{
"id": "person:Jesus.2",
"type": "person",
"confidence": 0.1596,
"match_method": "canonical",
"preferred_label": "Jesus"
},
{
"id": "keyterm:AskFor",
"type": "keyterm",
"confidence": 0.1596,
"match_method": "canonical",
"preferred_label": "Ask for"
},
{
"id": "keyterm:Salvation",
"type": "keyterm",
"confidence": 0.1596,
"match_method": "canonical",
"preferred_label": "Salvation"
},
{
"id": "deity:Satan",
"type": "deity",
"confidence": 0.1596,
"match_method": "canonical",
"preferred_label": "Satan"
},
{
"id": "keyterm:Forgive",
"type": "keyterm",
"confidence": 0.1596,
"match_method": "canonical",
"preferred_label": "Forgive"
},
{
"id": "keyterm:PutToTheTest",
"type": "keyterm",
"confidence": 0.1596,
"match_method": "canonical",
"preferred_label": "Put to the Test"
},
{
"id": "keyterm:Heaven",
"type": "keyterm",
"confidence": 0.1596,
"match_method": "canonical",
"preferred_label": "Sky"
},
{
"id": "keyterm:Disciple",
"type": "keyterm",
"confidence": 0.1596,
"match_method": "canonical",
"preferred_label": "Be a Disciple"
},
{
"id": "flora:Grain",
"type": "flora",
"confidence": 0.1591,
"match_method": "canonical",
"preferred_label": "Grain"
},
{
"id": "fauna:Bird",
"type": "fauna",
"confidence": 0.1591,
"match_method": "canonical",
"preferred_label": "Bird"
},
{
"id": "flora:Barley",
"type": "flora",
"confidence": 0.1591,
"match_method": "canonical",
"preferred_label": "Barley"
},
{
"id": "fauna:Rooster",
"type": "fauna",
"confidence": 0.1591,
"match_method": "canonical",
"preferred_label": "Rooster"
},
{
"id": "realia:Ship",
"type": "realia",
"confidence": 0.1591,
"match_method": "canonical",
"preferred_label": "Ship"
},
{
"id": "realia:House",
"type": "realia",
"confidence": 0.0996,
"match_method": "canonical",
"preferred_label": "House"
}
]
}
}
]