[
{
"content_id": "a58",
"reference_id": 0,
"version": "1.0.4",
"title": "铜币",
"media_type": "Image",
"index_reference": "铜币",
"language": "zhs",
"review_level": "None",
"content": "<h3>Image Content</h3>\n<block><p><img src='https://s3.amazonaws.com/cbbt-er.public/media/photos/a58/1000.jpg' alt='Image' width='480' /></p><p><a href='https://s3.amazonaws.com/cbbt-er.public/media/photos/a58/1000.jpg'>link</a></p></block>",
"associations": {
"passage": [
{
"start_ref": "40010026",
"start_ref_usfm": "MAT 10:26",
"end_ref": "40010033",
"end_ref_usfm": "MAT 10:33"
},
{
"start_ref": "41012038",
"start_ref_usfm": "MRK 12:38",
"end_ref": "41012044",
"end_ref_usfm": "MRK 12:44"
},
{
"start_ref": "42020045",
"start_ref_usfm": "LUK 20:45",
"end_ref": "42021004",
"end_ref_usfm": "LUK 21:4"
}
],
"resource": [],
"acai": [
{
"id": "deity:Lord",
"type": "deity",
"confidence": 0.3114,
"match_method": "canonical",
"preferred_label": "LORD"
},
{
"id": "keyterm:Fear",
"type": "keyterm",
"confidence": 0.3114,
"match_method": "canonical",
"preferred_label": "Fear"
},
{
"id": "realia:Treasury",
"type": "realia",
"confidence": 0.2514,
"match_method": "canonical",
"preferred_label": "Treasury"
},
{
"id": "keyterm:DailyLife",
"type": "keyterm",
"confidence": 0.2409,
"match_method": "canonical",
"preferred_label": "Daily Life"
},
{
"id": "keyterm:Heaven",
"type": "keyterm",
"confidence": 0.2409,
"match_method": "canonical",
"preferred_label": "Sky"
},
{
"id": "keyterm:Judgment",
"type": "keyterm",
"confidence": 0.2409,
"match_method": "canonical",
"preferred_label": "Judgment"
},
{
"id": "keyterm:Offering",
"type": "keyterm",
"confidence": 0.2409,
"match_method": "canonical",
"preferred_label": "Offering"
},
{
"id": "keyterm:Pray",
"type": "keyterm",
"confidence": 0.2409,
"match_method": "canonical",
"preferred_label": "Pray"
},
{
"id": "keyterm:Disciple",
"type": "keyterm",
"confidence": 0.2409,
"match_method": "canonical",
"preferred_label": "Be a Disciple"
},
{
"id": "realia:Lepton",
"type": "realia",
"confidence": 0.1991,
"match_method": "canonical",
"preferred_label": "Lepton"
},
{
"id": "fauna:Sparrow",
"type": "fauna",
"confidence": 0.19,
"match_method": "canonical",
"preferred_label": "Sparrow"
},
{
"id": "realia:Synagogue",
"type": "realia",
"confidence": 0.1809,
"match_method": "canonical",
"preferred_label": "Synagogue"
},
{
"id": "realia:Cloak",
"type": "realia",
"confidence": 0.1809,
"match_method": "canonical",
"preferred_label": "Cloak"
},
{
"id": "keyterm:Gehenna",
"type": "keyterm",
"confidence": 0.1795,
"match_method": "canonical",
"preferred_label": "Gehenna"
},
{
"id": "keyterm:Surely",
"type": "keyterm",
"confidence": 0.1705,
"match_method": "canonical",
"preferred_label": "Surely!"
},
{
"id": "keyterm:Command",
"type": "keyterm",
"confidence": 0.1705,
"match_method": "canonical",
"preferred_label": "To Command"
},
{
"id": "keyterm:Body.3",
"type": "keyterm",
"confidence": 0.1705,
"match_method": "canonical",
"preferred_label": "Body"
},
{
"id": "keyterm:Proclaim",
"type": "keyterm",
"confidence": 0.1705,
"match_method": "canonical",
"preferred_label": "Proclaim"
},
{
"id": "keyterm:Friendship",
"type": "keyterm",
"confidence": 0.1705,
"match_method": "canonical",
"preferred_label": "Friendship"
},
{
"id": "place:Hell",
"type": "place",
"confidence": 0.1705,
"match_method": "canonical",
"preferred_label": "Hell"
},
{
"id": "keyterm:True",
"type": "keyterm",
"confidence": 0.1705,
"match_method": "canonical",
"preferred_label": "True"
},
{
"id": "realia:Quadrans",
"type": "realia",
"confidence": 0.1286,
"match_method": "canonical",
"preferred_label": "Quadrans"
},
{
"id": "realia:Assarion",
"type": "realia",
"confidence": 0.1195,
"match_method": "canonical",
"preferred_label": "Assarion"
},
{
"id": "realia:Housetop",
"type": "realia",
"confidence": 0.1105,
"match_method": "canonical",
"preferred_label": "Housetop"
},
{
"id": "realia:House",
"type": "realia",
"confidence": 0.1105,
"match_method": "canonical",
"preferred_label": "House"
}
]
}
},
{
"content_id": "a59",
"reference_id": 0,
"version": "1.0.4",
"title": "铜币",
"media_type": "Image",
"index_reference": "铜币",
"language": "zhs",
"review_level": "None",
"content": "<h3>Image Content</h3>\n<block><p><img src='https://s3.amazonaws.com/cbbt-er.public/media/photos/a59/1000.jpg' alt='Image' width='480' /></p><p><a href='https://s3.amazonaws.com/cbbt-er.public/media/photos/a59/1000.jpg'>link</a></p></block>",
"associations": {
"passage": [
{
"start_ref": "40010026",
"start_ref_usfm": "MAT 10:26",
"end_ref": "40010033",
"end_ref_usfm": "MAT 10:33"
},
{
"start_ref": "41012038",
"start_ref_usfm": "MRK 12:38",
"end_ref": "41012044",
"end_ref_usfm": "MRK 12:44"
},
{
"start_ref": "42020045",
"start_ref_usfm": "LUK 20:45",
"end_ref": "42021004",
"end_ref_usfm": "LUK 21:4"
}
],
"resource": [],
"acai": [
{
"id": "deity:Lord",
"type": "deity",
"confidence": 0.3114,
"match_method": "canonical",
"preferred_label": "LORD"
},
{
"id": "keyterm:Fear",
"type": "keyterm",
"confidence": 0.3114,
"match_method": "canonical",
"preferred_label": "Fear"
},
{
"id": "realia:Treasury",
"type": "realia",
"confidence": 0.2514,
"match_method": "canonical",
"preferred_label": "Treasury"
},
{
"id": "keyterm:DailyLife",
"type": "keyterm",
"confidence": 0.2409,
"match_method": "canonical",
"preferred_label": "Daily Life"
},
{
"id": "keyterm:Heaven",
"type": "keyterm",
"confidence": 0.2409,
"match_method": "canonical",
"preferred_label": "Sky"
},
{
"id": "keyterm:Judgment",
"type": "keyterm",
"confidence": 0.2409,
"match_method": "canonical",
"preferred_label": "Judgment"
},
{
"id": "keyterm:Offering",
"type": "keyterm",
"confidence": 0.2409,
"match_method": "canonical",
"preferred_label": "Offering"
},
{
"id": "keyterm:Pray",
"type": "keyterm",
"confidence": 0.2409,
"match_method": "canonical",
"preferred_label": "Pray"
},
{
"id": "keyterm:Disciple",
"type": "keyterm",
"confidence": 0.2409,
"match_method": "canonical",
"preferred_label": "Be a Disciple"
},
{
"id": "realia:Lepton",
"type": "realia",
"confidence": 0.1991,
"match_method": "canonical",
"preferred_label": "Lepton"
},
{
"id": "fauna:Sparrow",
"type": "fauna",
"confidence": 0.19,
"match_method": "canonical",
"preferred_label": "Sparrow"
},
{
"id": "realia:Synagogue",
"type": "realia",
"confidence": 0.1809,
"match_method": "canonical",
"preferred_label": "Synagogue"
},
{
"id": "realia:Cloak",
"type": "realia",
"confidence": 0.1809,
"match_method": "canonical",
"preferred_label": "Cloak"
},
{
"id": "keyterm:Gehenna",
"type": "keyterm",
"confidence": 0.1795,
"match_method": "canonical",
"preferred_label": "Gehenna"
},
{
"id": "keyterm:Surely",
"type": "keyterm",
"confidence": 0.1705,
"match_method": "canonical",
"preferred_label": "Surely!"
},
{
"id": "keyterm:Command",
"type": "keyterm",
"confidence": 0.1705,
"match_method": "canonical",
"preferred_label": "To Command"
},
{
"id": "keyterm:Body.3",
"type": "keyterm",
"confidence": 0.1705,
"match_method": "canonical",
"preferred_label": "Body"
},
{
"id": "keyterm:Proclaim",
"type": "keyterm",
"confidence": 0.1705,
"match_method": "canonical",
"preferred_label": "Proclaim"
},
{
"id": "keyterm:Friendship",
"type": "keyterm",
"confidence": 0.1705,
"match_method": "canonical",
"preferred_label": "Friendship"
},
{
"id": "place:Hell",
"type": "place",
"confidence": 0.1705,
"match_method": "canonical",
"preferred_label": "Hell"
},
{
"id": "keyterm:True",
"type": "keyterm",
"confidence": 0.1705,
"match_method": "canonical",
"preferred_label": "True"
},
{
"id": "realia:Quadrans",
"type": "realia",
"confidence": 0.1286,
"match_method": "canonical",
"preferred_label": "Quadrans"
},
{
"id": "realia:Assarion",
"type": "realia",
"confidence": 0.1195,
"match_method": "canonical",
"preferred_label": "Assarion"
},
{
"id": "realia:Housetop",
"type": "realia",
"confidence": 0.1105,
"match_method": "canonical",
"preferred_label": "Housetop"
},
{
"id": "realia:House",
"type": "realia",
"confidence": 0.1105,
"match_method": "canonical",
"preferred_label": "House"
}
]
}
}
]